LICENSE
MANIFEST.in
README.md
requirements-web.txt
requirements.txt
setup.py
coolisf/__init__.py
coolisf/__main__.py
coolisf/__version__.py
coolisf/common.py
coolisf/config.py
coolisf/ergex.py
coolisf/ghub.py
coolisf/gold_extract.py
coolisf/lexsem.py
coolisf/main.py
coolisf/model.py
coolisf/morph.py
coolisf/shallow.py
coolisf/util.py
coolisf.egg-info/PKG-INFO
coolisf.egg-info/SOURCES.txt
coolisf.egg-info/dependency_links.txt
coolisf.egg-info/requires.txt
coolisf.egg-info/top_level.txt
coolisf/dao/__init__.py
coolisf/dao/cache.py
coolisf/dao/corpus.py
coolisf/dao/ruledb.py
coolisf/dao/textcorpus.py
coolisf/dao/tsdb.py
coolisf/dao/scripts/init_ace_cache.sql
coolisf/dao/scripts/init_corpus.sql
coolisf/dao/scripts/init_isf_cache.sql
coolisf/dao/scripts/init_ruledb.sql
coolisf/dao/scripts/ruleinfo_migrate.sql
coolisf/data/CCBY30_template.txt.gz
coolisf/data/__init__.py
coolisf/data/config.template.json.gz
coolisf/data/reader.py
coolisf/mappings/__init__.py
coolisf/mappings/ergpreds.py
coolisf/mappings/mwemap.py
coolisf/mappings/predsense.py
coolisf/parsers/__init__.py
coolisf/parsers/dmrs_str.py
coolisf/processors/__init__.py
coolisf/processors/base.py
coolisf/processors/basic.py
coolisf/processors/jp_adv.py
coolisf/processors/jp_basic.py
coolisf/rest/__init__.py
coolisf/rest/admin.py
coolisf/rest/apps.py
coolisf/rest/models.py
coolisf/rest/tests.py
coolisf/rest/urls.py
coolisf/rest/views.py
test/test_coolisf.py
test/test_corpus_dao.py
test/test_dao.py
test/test_ew_map.py
test/test_ghub.py
test/test_goldgen.py
test/test_jacy.py
test/test_lexsem.py
test/test_miner.py
test/test_model.py
test/test_parser.py
test/test_prep.py
test/test_shallow.py
test/test_tools.py
test/test_virgo.py