Metadata-Version: 2.1
Name: coolisf
Version: 0.2.3
Summary: A Python 3 implementation of the Integrated Semantic Framework that provides computational deep semantic analysis by combining structural semantics from construction grammars and lexical semantics from ontologies in a single representation.
Home-page: https://github.com/letuananh/intsem.fx/
Author: Le Tuan Anh
Author-email: tuananh.ke@gmail.com
License: MIT License
Project-URL: Bug Tracker, https://github.com/letuananh/intsem.fx/issues
Project-URL: Source Code, https://github.com/letuananh/intsem.fx
Keywords: linguistics,analysis,semantics,meaning,nlp,HPSG,ERG,MRS,DMRS,grammar,Sign-based Construction Grammar,wordnet,wsd,word-sense disambiguation
Platform: any
Classifier: Programming Language :: Python
Classifier: Development Status :: 5 - Production/Stable
Classifier: Natural Language :: English
Classifier: Natural Language :: Japanese
Classifier: Natural Language :: Indonesian
Classifier: Natural Language :: Chinese (Simplified)
Classifier: Natural Language :: Chinese (Traditional)
Classifier: Environment :: Console
Classifier: Intended Audience :: Developers
Classifier: License :: OSI Approved :: MIT License
Classifier: Operating System :: OS Independent
Classifier: Topic :: Software Development :: Libraries :: Python Modules
Requires-Python: >=3.6
